rtl/register_file.v
// File: rtl/register_file.v
// Description: 16-bit Register File (16 individual slots for variables)

module register_file (
    input  wire        clk,
    input  wire        rst_n,
    
    // Write Port (Saving data)
    input  wire        write_en,   // From Decoder (mem_write or reg_write)
    input  wire [3:0]  write_addr, // Which slot to save to (0 to 15)
    input  wire [15:0] write_data, // The actual data to save
    
    // Read Ports (Sending data to ALU)
    input  wire [3:0]  read_addr_a, // Which slot to read for Operand A
    input  wire [3:0]  read_addr_b, // Which slot to read for Operand B
    output wire [15:0] read_data_a,
    output wire [15:0] read_data_b
);

    // Create an array of 16 registers, each 16 bits wide
    reg [15:0] registers [0:15];
    integer i;

    // Read logic: Asynchronous (immediate)
    assign read_data_a = registers[read_addr_a];
    assign read_data_b = registers[read_addr_b];

    // Write logic: Synchronous (happens exactly on the clock tick)
    always @(posedge clk or negedge rst_n) begin
        if (!rst_n) begin
            // On reset, clear all 16 registers to 0
            for (i = 0; i < 16; i = i + 1) begin
                registers[i] <= 16'h0000;
            end
        end 
        else if (write_en) begin
            registers[write_addr] <= write_data; // Save the new variable!
        end
    end

endmodule

rtl/clock_gating_unit.v
// File: rtl/clock_gating_unit.v
// Description: Glitch-free Integrated Clock Gating (ICG) Cell

module clock_gating_unit (
    input  wire clk_in,   // Main continuous system clock
    input  wire enable,   // Signal to turn the clock on/off
    output wire clk_out   // The safe, gated clock going to your modules
);

    reg latch_en;

    // The Latch: Only captures the 'enable' signal when the clock is LOW.
    // This prevents nasty voltage spikes from destroying the logic.
    always @(clk_in or enable) begin
        if (!clk_in) begin
            latch_en <= enable; 
        end
    end

    // The AND Gate: Safely turns the clock off.
    assign clk_out = clk_in & latch_en;

endmodule

rtl/alu.v
// File: rtl/alu.v
// Description: Low-Power Arithmetic Logic Unit with Operand Isolation

module alu (
    input  wire        alu_en,     // Comes from the Decoder
    input  wire [3:0]  opcode,     // To know which math operation to do
    input  wire [15:0] operand_a,  // First number
    input  wire [15:0] operand_b,  // Second number
    
    output reg  [15:0] alu_result, // The answer
    output wire        zero_flag   // High if result is exactly 0
);

    // ==========================================
    // LOW POWER TRICK: OPERAND ISOLATION
    // If alu_en is 0, block the inputs. 
    // This stops internal transistors from toggling!
    // ==========================================
    wire [15:0] iso_a = alu_en ? operand_a : 16'h0000;
    wire [15:0] iso_b = alu_en ? operand_b : 16'h0000;

    always @(*) begin
        if (!alu_en) begin
            alu_result = 16'h0000; // Keep output quiet when off
        end 
        else begin
            // Perform math based on the Opcode
            case (opcode)
                4'h3: alu_result = iso_a + iso_b; // ADD (Our main process op)
                4'h6: alu_result = iso_a - iso_b; // SUBTRACT (Example)
                4'h7: alu_result = iso_a & iso_b; // BITWISE AND (Example)
                
                // If it's a math opcode we don't recognize, output 0
                default: alu_result = 16'h0000; 
            endcase
        end
    end

    // The zero flag is useful later if we want to add "Branch if Equal" instructions
    assign zero_flag = (alu_result == 16'h0000);

endmodule

rtl/instruction_decoder.v
// File: rtl/instruction_decoder.v
// Description: The "Brain" of the IoT Core. Decodes 16-bit instructions into control signals.

module instruction_decoder (
    input  wire [15:0] instruction, // The 16-bit hex code from Instruction Memory
    
    // Control Signals Output
    output reg         sleep_en,    // Tells the PC to freeze
    output reg         alu_en,      // Turns on the Math Unit (ALU)
    output reg         mem_write,   // Allows saving data to RAM
    
    // Data Signals Output
    output reg  [3:0]  opcode,      // The action to perform
    output reg  [3:0]  dest_reg,    // Where to save the result
    output reg  [3:0]  src_reg      // The data to use
);

    // Combinational Logic: Reacts instantly to a new instruction
    always @(*) begin
        // 1. Default Power-Saving State (Everything OFF)
        sleep_en  = 1'b0;
        alu_en    = 1'b0;
        mem_write = 1'b0;

        // 2. Slice the 16-bit instruction into its parts
        opcode   = instruction[15:12];
        dest_reg = instruction[11:8];
        src_reg  = instruction[7:4];

        // 3. Generate Control Signals based on the Opcode
        case (opcode)
            4'h1: ; // INIT/WAKEUP (No special hardware action needed yet)
            
            4'h2: ; // READ SENSOR (Would trigger GPIO pins in a full SoC)
            
            4'h3: begin 
                alu_en = 1'b1;     // OP 3: ALU PROCESS -> Wake up the ALU!
            end
            
            4'h4: begin 
                mem_write = 1'b1;  // OP 4: STORE DATA -> Turn on Data RAM
            end
            
            4'hF: begin 
                sleep_en = 1'b1;   // OP F: SLEEP -> Send the freeze signal to PC!
            end
            
            default: ; // NOP (Do nothing)
        endcase
    end

endmodule

rtl/instruction_memory.v
// File: rtl/instruction_memory.v
module instruction_memory (
    input  wire [15:0] pc_addr,      
    output reg  [15:0] instruction   
);

    reg [15:0] rom [0:255];

    initial begin
        rom[8'h00] = 16'h1001;  // WAKE UP
        rom[8'h01] = 16'h2025;  // READ SENSOR
        rom[8'h02] = 16'h3050;  // ALU PROCESS
        rom[8'h03] = 16'h4000;  // STORE DATA
        rom[8'h04] = 16'hFFFF;  // SLEEP COMMAND
        rom[8'h05] = 16'h0000;  // NOP 
    end

    always @(*) begin
        instruction = rom[pc_addr[7:0]]; 
    end
endmodule

rtl/program_counter.v
// File: rtl/program_counter.v
module program_counter (
    input  wire        clk,       
    input  wire        rst_n,     
    input  wire        sleep_en,  // High = Freeze PC to save power
    input  wire        pc_load,   
    input  wire [15:0] pc_in,     
    output reg  [15:0] pc_out     
);

    always @(posedge clk or negedge rst_n) begin
        if (!rst_n) begin
            pc_out <= 16'h0000;      
        end 
        else if (sleep_en) begin
            pc_out <= pc_out;        // SLEEP: Hold value (Zero dynamic power!)
        end 
        else if (pc_load) begin
            pc_out <= pc_in;         
        end 
        else begin
            pc_out <= pc_out + 1'b1; 
        end
    end
endmodule

rtl/iot_core_top.v
// File: rtl/iot_core_top.v
// Description: The fully wired 16-bit Low-Power IoT Microprocessor!

module iot_core_top (
    input  wire        clk,          // Master Clock 
    input  wire        rst_n,        // Master Reset
    input  wire        wake_up,      // External wake-up pin
    
    // NEW OUTPUT PINS to prevent Yosys from deleting the design!
    output wire [15:0] current_pc,   // Let the outside world see the address
    output wire        is_sleeping   // Let the outside world know if it's asleep
);

    // ==========================================
    // INTERNAL WIRES
    // ==========================================
    wire [15:0] pc_addr, instruction;
    wire        sleep_en, alu_en, reg_write;
    wire [3:0]  opcode, dest_reg, src_reg;
    wire [15:0] alu_result, reg_val_a, reg_val_b;
    wire        alu_zero;
    
    wire clk_alu, clk_reg;
    wire active_sleep = sleep_en & ~wake_up;

    // ==========================================
    // MODULE INSTANTIATIONS
    // ==========================================

    program_counter u_pc (
        .clk(clk), .rst_n(rst_n), .sleep_en(active_sleep),
        .pc_load(1'b0), .pc_in(16'h0000), .pc_out(pc_addr)
    );

    instruction_memory u_imem (
        .pc_addr(pc_addr), .instruction(instruction)
    );

    instruction_decoder u_decoder (
        .instruction(instruction),
        .sleep_en(sleep_en), .alu_en(alu_en), .mem_write(reg_write),
        .opcode(opcode), .dest_reg(dest_reg), .src_reg(src_reg)
    );

    clock_gating_unit u_cg_alu (
        .clk_in(clk), .enable(alu_en), .clk_out(clk_alu)
    );

    alu u_alu (
        .alu_en(alu_en), .opcode(opcode),
        .operand_a(reg_val_a), .operand_b(reg_val_b),
        .alu_result(alu_result), .zero_flag(alu_zero)
    );

    wire reg_active = reg_write | alu_en; 
    clock_gating_unit u_cg_reg (
        .clk_in(clk), .enable(reg_active), .clk_out(clk_reg)
    );

    register_file u_regfile (
        .clk(clk_reg), .rst_n(rst_n), 
        .write_en(reg_write), .write_addr(dest_reg), .write_data(alu_result),
        .read_addr_a(src_reg), .read_addr_b(4'h0), 
        .read_data_a(reg_val_a), .read_data_b(reg_val_b)
    );

    // ==========================================
    // OUTPUT CONNECTIONS
    // ==========================================
    // Drive the external pins with our internal signals
    assign current_pc = pc_addr;
    assign is_sleeping = sleep_en;

endmodule

tb/iot_core_tb.v
// File: tb/iot_core_tb.v
// Description: The Master Testbench for the Low-Power IoT Core

`timescale 1ns/1ps

module iot_core_tb;
    reg clk;
    reg rst_n;
    reg wake_up;

    // Plug in our completed microprocessor!
    iot_core_top u_core (
        .clk(clk),
        .rst_n(rst_n),
        .wake_up(wake_up)
    );

    // Generate Master Clock (10ns period -> 100MHz)
    always #5 clk = ~clk;

    initial begin
        // Setup Waveform output
        $dumpfile("sim/core_wave.vcd");
        $dumpvars(0, iot_core_tb);

        // 1. Initialize System (Powering On)
        clk = 0;
        rst_n = 0;
        wake_up = 0;

        // 2. Release Reset to start execution
        #15 rst_n = 1;

        // 3. Let the processor run its embedded program
        // It will execute the instructions and then hit FFFF (SLEEP)
        #80;

        // 4. The chip is now asleep. Let's trigger an external Wake-Up interrupt!
        #20 wake_up = 1; 
        #10 wake_up = 0; 

        // Let it run for a few more cycles after waking up
        #50;
        
        $finish;
    end
endmodule

sim/core_wave.vcd
$date
	Tue Mar 24 11:26:28 2026
$end
$version
	Icarus Verilog
$end
$timescale
	1ps
$end
$scope module iot_core_tb $end
$var reg 1 ! clk $end
$var reg 1 " rst_n $end
$var reg 1 # wake_up $end
$scope module u_core $end
$var wire 1 $ active_sleep $end
$var wire 1 ! clk $end
$var wire 16 % current_pc [15:0] $end
$var wire 1 & is_sleeping $end
$var wire 1 ' reg_active $end
$var wire 1 " rst_n $end
$var wire 1 # wake_up $end
$var wire 4 ( src_reg [3:0] $end
$var wire 1 ) sleep_en $end
$var wire 1 * reg_write $end
$var wire 16 + reg_val_b [15:0] $end
$var wire 16 , reg_val_a [15:0] $end
$var wire 16 - pc_addr [15:0] $end
$var wire 4 . opcode [3:0] $end
$var wire 16 / instruction [15:0] $end
$var wire 4 0 dest_reg [3:0] $end
$var wire 1 1 clk_reg $end
$var wire 1 2 clk_alu $end
$var wire 1 3 alu_zero $end
$var wire 16 4 alu_result [15:0] $end
$var wire 1 5 alu_en $end
$scope module u_alu $end
$var wire 1 3 zero_flag $end
$var wire 16 6 operand_b [15:0] $end
$var wire 16 7 operand_a [15:0] $end
$var wire 4 8 opcode [3:0] $end
$var wire 16 9 iso_b [15:0] $end
$var wire 16 : iso_a [15:0] $end
$var wire 1 5 alu_en $end
$var reg 16 ; alu_result [15:0] $end
$upscope $end
$scope module u_cg_alu $end
$var wire 1 ! clk_in $end
$var wire 1 2 clk_out $end
$var wire 1 5 enable $end
$var reg 1 < latch_en $end
$upscope $end
$scope module u_cg_reg $end
$var wire 1 ! clk_in $end
$var wire 1 1 clk_out $end
$var wire 1 ' enable $end
$var reg 1 = latch_en $end
$upscope $end
$scope module u_decoder $end
$var wire 16 > instruction [15:0] $end
$var reg 1 5 alu_en $end
$var reg 4 ? dest_reg [3:0] $end
$var reg 1 * mem_write $end
$var reg 4 @ opcode [3:0] $end
$var reg 1 ) sleep_en $end
$var reg 4 A src_reg [3:0] $end
$upscope $end
$scope module u_imem $end
$var wire 16 B pc_addr [15:0] $end
$var reg 16 C instruction [15:0] $end
$upscope $end
$scope module u_pc $end
$var wire 1 ! clk $end
$var wire 16 D pc_in [15:0] $end
$var wire 1 E pc_load $end
$var wire 1 " rst_n $end
$var wire 1 $ sleep_en $end
$var reg 16 F pc_out [15:0] $end
$upscope $end
$scope module u_regfile $end
$var wire 1 1 clk $end
$var wire 4 G read_addr_a [3:0] $end
$var wire 4 H read_addr_b [3:0] $end
$var wire 16 I read_data_a [15:0] $end
$var wire 16 J read_data_b [15:0] $end
$var wire 1 " rst_n $end
$var wire 4 K write_addr [3:0] $end
$var wire 16 L write_data [15:0] $end
$var wire 1 * write_en $end
$var integer 32 M i [31:0] $end
$upscope $end
$upscope $end
$upscope $end
$enddefinitions $end
#0
$dumpvars
b10000 M
b0 L
b0 K
b0 J
b0 I
b0 H
b0 G
b0 F
0E
b0 D
b1000000000001 C
b0 B
b0 A
b1 @
b0 ?
b1000000000001 >
0=
0<
b0 ;
b0 :
b0 9
b1 8
b0 7
b0 6
05
b0 4
13
02
01
b0 0
b1000000000001 /
b1 .
b0 -
b0 ,
b0 +
0*
0)
b0 (
0'
0&
b0 %
0$
0#
0"
0!
$end
#5000
1!
#10000
0!
#15000
b10 (
b10 A
b10 G
b10 .
b10 8
b10 @
b10000000100101 /
b10000000100101 >
b10000000100101 C
b1 %
b1 -
b1 B
b1 F
1!
1"
#20000
0!
#25000
1'
15
b101 (
b101 A
b101 G
b11 .
b11 8
b11 @
b11000001010000 /
b11000001010000 >
b11000001010000 C
b10 %
b10 -
b10 B
b10 F
1!
#30000
1<
1=
0!
#35000
1*
b0 (
b0 A
b0 G
b100 .
b100 8
b100 @
05
b100000000000000 /
b100000000000000 >
b100000000000000 C
b11 %
b11 -
b11 B
b11 F
12
11
1!
#40000
0<
02
01
0!
#45000
1$
0'
1&
1)
b1111 (
b1111 A
b1111 G
b1111 0
b1111 ?
b1111 K
b1111 .
b1111 8
b1111 @
0*
b1111111111111111 /
b1111111111111111 >
b1111111111111111 C
b100 %
b100 -
b100 B
b100 F
11
1!
#50000
0=
01
0!
#55000
1!
#60000
0!
#65000
1!
#70000
0!
#75000
1!
#80000
0!
#85000
1!
#90000
0!
#95000
1!
#100000
0!
#105000
1!
#110000
0!
#115000
0$
1!
1#
#120000
0!
#125000
b0 (
b0 A
b0 G
b0 0
b0 ?
b0 K
b0 .
b0 8
b0 @
0&
0)
b0 /
b0 >
b0 C
b101 %
b101 -
b101 B
b101 F
0$
1!
0#
#130000
0!
#135000
bx ,
bx 7
bx I
bx (
bx A
bx G
bx 0
bx ?
bx K
bx .
bx 8
bx @
bx /
bx >
bx C
b110 %
b110 -
b110 B
b110 F
1!
#140000
0!
#145000
b111 %
b111 -
b111 B
b111 F
1!
#150000
0!
#155000
b1000 %
b1000 -
b1000 B
b1000 F
1!
#160000
0!
#165000
b1001 %
b1001 -
b1001 B
b1001 F
1!
#170000
0!
#175000
b1010 %
b1010 -
b1010 B
b1010 F
1!
